PySide6_AceEditor/__init__.py
PySide6_AceEditor/__main__.py
PySide6_AceEditor/code_frame.py
PySide6_AceEditor/constants.py
PySide6_AceEditor/core.py
PySide6_AceEditor/testWindow.py
PySide6_AceEditor/ui_testWindow.py
PySide6_AceEditor/utils.py
PySide6_AceEditor/runtime/ace.min.js
PySide6_AceEditor/runtime/ext-beautify.js
PySide6_AceEditor/runtime/ext-code_lens.js
PySide6_AceEditor/runtime/ext-command_bar.js
PySide6_AceEditor/runtime/ext-diff.js
PySide6_AceEditor/runtime/ext-elastic_tabstops_lite.js
PySide6_AceEditor/runtime/ext-emmet.js
PySide6_AceEditor/runtime/ext-error_marker.js
PySide6_AceEditor/runtime/ext-hardwrap.js
PySide6_AceEditor/runtime/ext-inline_autocomplete.js
PySide6_AceEditor/runtime/ext-keybinding_menu.js
PySide6_AceEditor/runtime/ext-language_tools.js
PySide6_AceEditor/runtime/ext-linking.js
PySide6_AceEditor/runtime/ext-modelist.js
PySide6_AceEditor/runtime/ext-options.js
PySide6_AceEditor/runtime/ext-prompt.js
PySide6_AceEditor/runtime/ext-rtl.js
PySide6_AceEditor/runtime/ext-searchbox.js
PySide6_AceEditor/runtime/ext-settings_menu.js
PySide6_AceEditor/runtime/ext-simple_tokenizer.js
PySide6_AceEditor/runtime/ext-spellcheck.js
PySide6_AceEditor/runtime/ext-split.js
PySide6_AceEditor/runtime/ext-static_highlight.js
PySide6_AceEditor/runtime/ext-statusbar.js
PySide6_AceEditor/runtime/ext-textarea.js
PySide6_AceEditor/runtime/ext-themelist.js
PySide6_AceEditor/runtime/ext-whitespace.js
PySide6_AceEditor/runtime/keybinding-emacs.js
PySide6_AceEditor/runtime/keybinding-sublime.js
PySide6_AceEditor/runtime/keybinding-vim.js
PySide6_AceEditor/runtime/keybinding-vscode.js
PySide6_AceEditor/runtime/mode-abap.js
PySide6_AceEditor/runtime/mode-abc.js
PySide6_AceEditor/runtime/mode-actionscript.js
PySide6_AceEditor/runtime/mode-ada.js
PySide6_AceEditor/runtime/mode-alda.js
PySide6_AceEditor/runtime/mode-apache_conf.js
PySide6_AceEditor/runtime/mode-apex.js
PySide6_AceEditor/runtime/mode-applescript.js
PySide6_AceEditor/runtime/mode-aql.js
pyside6_aceeditor-0.1.0.dist-info/METADATA
pyside6_aceeditor-0.1.0.dist-info/WHEEL
pyside6_aceeditor-0.1.0.dist-info/entry_points.txt
pyside6_aceeditor-0.1.0.dist-info/top_level.txt
pyside6_aceeditor-0.1.0.dist-info/RECORD
