Metadata-Version: 2.4
Name: PySide6-AceEditor
Version: 0.1.0
Summary: 基于PySide6的Ace编辑器组件，内置Ace Editor前端资源
Home-page: https://github.com/wangruoyuyuyu/PySide6-AceEditor/
Author: wry
Author-email: wry_by01@outlook.com
Requires-Python: >=3.8
Requires-Dist: PySide6>=6.5.0
Requires-Dist: websockets>=12.0
Requires-Dist: pyperclip>=1.8.2
Dynamic: author
Dynamic: author-email
Dynamic: home-page
Dynamic: requires-dist
Dynamic: requires-python
Dynamic: summary
